genesis/__init__.py
genesis/client.py
genesis_core/__init__.py
genesis_core/example.py
genesis_core/genesis_core/__init__.py
genesis_core/genesis_core/errors.py
genesis_core/genesis_core/factory.py
genesis_core/genesis_core/governance.py
genesis_core/genesis_core/logging_config.py
genesis_core/genesis_core/memory.py
genesis_core/genesis_core/orchestrator.py
genesis_core/genesis_core/schemas.py
genesis_core/genesis_core/sdk.py
genesis_core/genesis_core/sandbox/__init__.py
genesis_core/genesis_core/sandbox/docker_client.py
genesis_server/__init__.py
genesis_server/config.py
genesis_server/database.py
genesis_server/ingestion.py
genesis_server/main.py
genesis_server/rag.py
genesis_framework_sdk-0.1.1.dist-info/METADATA
genesis_framework_sdk-0.1.1.dist-info/WHEEL
genesis_framework_sdk-0.1.1.dist-info/top_level.txt
genesis_framework_sdk-0.1.1.dist-info/RECORD
