Metadata-Version: 2.1
Name: genesis-framework-sdk
Version: 0.1.1
Summary: The OS for Recursive Agentic Intelligence
Author: Genesis Inc.
Classifier: Programming Language :: Python :: 3
Classifier: License :: OSI Approved :: MIT License
Requires-Dist: requests
Requires-Dist: pydantic
